{
  "stable": {
    "version": "1.12.6",
    "arches": {
      "amd64": {
        "url": "https://julialang-s3.julialang.org/bin/linux/x64/1.12/julia-1.12.6-linux-x86_64.tar.gz",
        "sha256": "bbabf3bef19421a9dbd24a767d807606ab85e444323b5a1c73ffe293fa3d079a"
      },
      "i386": {
        "url": "https://julialang-s3.julialang.org/bin/linux/x86/1.12/julia-1.12.6-linux-i686.tar.gz",
        "sha256": "2ab43d56adfe96c7b0b9ddab0e049f54f49df24049ec8b482c26737c42af28cd"
      },
      "arm64v8": {
        "url": "https://julialang-s3.julialang.org/bin/linux/aarch64/1.12/julia-1.12.6-linux-aarch64.tar.gz",
        "sha256": "029b93b857bd0ffd627f9a8580d3bbaa63daf008d7b7aed02fbceb8fd57c4899"
      },
      "darwin-amd64": {
        "url": "https://julialang-s3.julialang.org/bin/mac/x64/1.12/julia-1.12.6-mac64.tar.gz",
        "sha256": "1a70b7c606d6bac38a246e722369e5b30914dccf9378499d2712fb3bd282642c"
      },
      "darwin-arm64v8": {
        "url": "https://julialang-s3.julialang.org/bin/mac/aarch64/1.12/julia-1.12.6-macaarch64.tar.gz",
        "sha256": "277d82fbd2eda99d0963b3e41f3dc979d7486f181399f8430fb637318ccd6a31"
      },
      "windows-amd64": {
        "url": "https://julialang-s3.julialang.org/bin/winnt/x64/1.12/julia-1.12.6-win64.exe",
        "sha256": "de2d50f23995d71c224423a4872673a4e9be2c9676fc975cd90b25fc3a5e6cb6"
      },
      "windows-i386": {
        "url": "https://julialang-s3.julialang.org/bin/winnt/x86/1.12/julia-1.12.6-win32.exe",
        "sha256": "9961c418b28c29d2102b2d40adfbae057d370820039fc29768055d19a9b6d44b"
      },
      "freebsd-amd64": {
        "url": "https://julialang-s3.julialang.org/bin/freebsd/x64/1.12/julia-1.12.6-freebsd-x86_64.tar.gz",
        "sha256": "f0c4d88161157034d85a0db1752e5b2cf1f2bb3dd860135aaf0d1342db9bfedd"
      }
    },
    "variants": [
      "trixie",
      "bookworm",
      "windows/servercore-ltsc2025",
      "windows/servercore-ltsc2022"
    ]
  },
  "1.10": {
    "version": "1.10.11",
    "arches": {
      "amd64": {
        "url": "https://julialang-s3.julialang.org/bin/linux/x64/1.10/julia-1.10.11-linux-x86_64.tar.gz",
        "sha256": "fb49c6b174600cd2051e37ba3f7330f8acf06dd00bce609bab6611387fdb37bf"
      },
      "i386": {
        "url": "https://julialang-s3.julialang.org/bin/linux/x86/1.10/julia-1.10.11-linux-i686.tar.gz",
        "sha256": "8cf274a08194803e2b0bb5f406e143acd535284efee750fe5b7316883bd12ec9"
      },
      "arm64v8": {
        "url": "https://julialang-s3.julialang.org/bin/linux/aarch64/1.10/julia-1.10.11-linux-aarch64.tar.gz",
        "sha256": "3004a980420e5f3a08847f44db9699105d9febc519205af52764fc97eb12c6b2"
      },
      "ppc64le": {
        "url": "https://julialang-s3.julialang.org/bin/linux/ppc64le/1.10/julia-1.10.11-linux-ppc64le.tar.gz",
        "sha256": "2dee344a4de2a1f0ef3ac715dcf8c7d2a77466f120ad8065d06f688ea9f595d9"
      },
      "darwin-amd64": {
        "url": "https://julialang-s3.julialang.org/bin/mac/x64/1.10/julia-1.10.11-mac64.tar.gz",
        "sha256": "bdc6f52ee4fdcf13f0d0e2480733742b7eefb7fbfc66c518daca6e19e804f34b"
      },
      "darwin-arm64v8": {
        "url": "https://julialang-s3.julialang.org/bin/mac/aarch64/1.10/julia-1.10.11-macaarch64.tar.gz",
        "sha256": "bd5706c10dceffeebe56d2d3f371e3d8d4b27195cad7489f22f6292af907f05b"
      },
      "windows-amd64": {
        "url": "https://julialang-s3.julialang.org/bin/winnt/x64/1.10/julia-1.10.11-win64.exe",
        "sha256": "e3cca35e623ea393474b44c1d7e37f15c8e67176f85a33959b8ce0ae21f9e80d"
      },
      "windows-i386": {
        "url": "https://julialang-s3.julialang.org/bin/winnt/x86/1.10/julia-1.10.11-win32.exe",
        "sha256": "21e9923b72677d01a75d3abfb9caefeba88ef89b2d4049d68d4b67b69ea6f5a3"
      },
      "freebsd-amd64": {
        "url": "https://julialang-s3.julialang.org/bin/freebsd/x64/1.10/julia-1.10.11-freebsd-x86_64.tar.gz",
        "sha256": "99ee7a28a35de5e2447875f0355893bd9f30149c908c56af48bd59e375a718e5"
      }
    },
    "variants": [
      "trixie",
      "bookworm",
      "windows/servercore-ltsc2025",
      "windows/servercore-ltsc2022"
    ]
  },
  "1.11": {
    "version": "1.11.9",
    "arches": {
      "amd64": {
        "url": "https://julialang-s3.julialang.org/bin/linux/x64/1.11/julia-1.11.9-linux-x86_64.tar.gz",
        "sha256": "b36363356d7a05eaf8b7b9e7a91c710f6bd3d2940be4d4e6d14b9a9f2927de35"
      },
      "i386": {
        "url": "https://julialang-s3.julialang.org/bin/linux/x86/1.11/julia-1.11.9-linux-i686.tar.gz",
        "sha256": "74df5031a93bce45e30582a71bf70f4ba983ff42f6eaf54eb9effb6e124604ca"
      },
      "arm64v8": {
        "url": "https://julialang-s3.julialang.org/bin/linux/aarch64/1.11/julia-1.11.9-linux-aarch64.tar.gz",
        "sha256": "a2071f0654d1d6af4381cba650b9f790f5f8bb7a570e51e378de8bcf67ff623e"
      },
      "ppc64le": {
        "url": "https://julialang-s3.julialang.org/bin/linux/ppc64le/1.11/julia-1.11.9-linux-ppc64le.tar.gz",
        "sha256": "3c25d5bf70d65da5859d65b34d17646dd1b3f1b50ea2090d13e63171d6dbf861"
      },
      "darwin-amd64": {
        "url": "https://julialang-s3.julialang.org/bin/mac/x64/1.11/julia-1.11.9-mac64.tar.gz",
        "sha256": "f7b49c3ddb22389dfab2c1d8d26fa4bef540ee8195650d8c502daa9c1c2edf92"
      },
      "darwin-arm64v8": {
        "url": "https://julialang-s3.julialang.org/bin/mac/aarch64/1.11/julia-1.11.9-macaarch64.tar.gz",
        "sha256": "ed903d0d337036fc3a68414bfca5f73107af162678ef76b52e42e84e25f33bd7"
      },
      "windows-amd64": {
        "url": "https://julialang-s3.julialang.org/bin/winnt/x64/1.11/julia-1.11.9-win64.exe",
        "sha256": "747ff8983fa183e0e35e618c9212815cba0b3ad29a44eaac039acc755a0d91b6"
      },
      "windows-i386": {
        "url": "https://julialang-s3.julialang.org/bin/winnt/x86/1.11/julia-1.11.9-win32.exe",
        "sha256": "cf083fe27e5dd9293175708625bb5d911250e29a6b7e8ecd95852228ffc6d66f"
      },
      "freebsd-amd64": {
        "url": "https://julialang-s3.julialang.org/bin/freebsd/x64/1.11/julia-1.11.9-freebsd-x86_64.tar.gz",
        "sha256": "275c0bc46f50b58a584a30f29fda20b757b8f6a1dff4cf664b0168724ff3d373"
      }
    },
    "variants": [
      "trixie",
      "bookworm",
      "windows/servercore-ltsc2025",
      "windows/servercore-ltsc2022"
    ]
  },
  "rc": {
    "version": "1.13.0-rc1",
    "arches": {
      "amd64": {
        "url": "https://julialang-s3.julialang.org/bin/linux/x64/1.13/julia-1.13.0-rc1-linux-x86_64.tar.gz",
        "sha256": "94c501d83aa46fad188894a31db093c6d065bbab94346645c775876066ec1b78"
      },
      "i386": {
        "url": "https://julialang-s3.julialang.org/bin/linux/x86/1.13/julia-1.13.0-rc1-linux-i686.tar.gz",
        "sha256": "1e758cfe0ba45a9b5313ff732ff5aa0d4f1927129e1b207e5e6c51e35ed9abb4"
      },
      "arm64v8": {
        "url": "https://julialang-s3.julialang.org/bin/linux/aarch64/1.13/julia-1.13.0-rc1-linux-aarch64.tar.gz",
        "sha256": "0e08d6410e76a51b6825aed34c9e20fd5778b35cc4b406dd8eb8bd402d8df705"
      },
      "darwin-amd64": {
        "url": "https://julialang-s3.julialang.org/bin/mac/x64/1.13/julia-1.13.0-rc1-mac64.tar.gz",
        "sha256": "cba07a87a0909bd40984880a6743e1575582b63c62dc7ee050c77c61b9f0bf33"
      },
      "darwin-arm64v8": {
        "url": "https://julialang-s3.julialang.org/bin/mac/aarch64/1.13/julia-1.13.0-rc1-macaarch64.tar.gz",
        "sha256": "0d3e75402a54f9758b2e160d1327d953272799c3330862e61dc0be788e0452b9"
      },
      "windows-amd64": {
        "url": "https://julialang-s3.julialang.org/bin/winnt/x64/1.13/julia-1.13.0-rc1-win64.exe",
        "sha256": "58e3b22f9e99b94f99bd81d26ca049ef1b4fd9aa0f58e7eb0d984f56cd76d4cf"
      },
      "windows-i386": {
        "url": "https://julialang-s3.julialang.org/bin/winnt/x86/1.13/julia-1.13.0-rc1-win32.exe",
        "sha256": "5135478606ca2445bcb525f0d962455877f3042e7ccce7ec16d7326dbed5fc8e"
      },
      "freebsd-amd64": {
        "url": "https://julialang-s3.julialang.org/bin/freebsd/x64/1.13/julia-1.13.0-rc1-freebsd-x86_64.tar.gz",
        "sha256": "8f004b8ae3113b19fab734e0a86ff6bc3887ca0eeec28c0537b9831efb8de091"
      }
    },
    "variants": [
      "trixie",
      "bookworm",
      "windows/servercore-ltsc2025",
      "windows/servercore-ltsc2022"
    ]
  }
}
